Metadata-Version: 2.1
Name: paramize
Version: 0.1.0
Summary: Python SDK for Paramize
Author: Paramize
Author-email: dev@wingify.com
License: Apache License 2.0
Classifier: Development Status :: 5 - Production/Stable
Classifier: Environment :: Web Environment
Classifier: Intended Audience :: Developers
Classifier: License :: OSI Approved :: Apache Software License
Classifier: Operating System :: OS Independent
Classifier: Programming Language :: Python
Classifier: Programming Language :: Python :: 3.7
Requires-Python: >3.7
License-File: LICENSE
License-File: NOTICE
